{"ongoing_trials": {}, "hyperparameters": {"space": [{"class_name": "Choice", "config": {"name": "embedding_dim", "default": 4, "conditions": [], "values": [4, 8], "ordered": true}}, {"class_name": "Choice", "config": {"name": "conv_filters", "default": 4, "conditions": [], "values": [4, 8], "ordered": true}}, {"class_name": "Choice", "config": {"name": "lstm_units", "default": 4, "conditions": [], "values": [4, 8], "ordered": true}}, {"class_name": "Choice", "config": {"name": "learning_rate", "default": 0.01, "conditions": [], "values": [0.01, 0.001, 0.0001], "ordered": true}}], "values": {"embedding_dim": 4, "conv_filters": 4, "lstm_units": 4, "learning_rate": 0.01}}, "start_order": ["00", "01", "02", "03", "04", "05", "06", "07", "08", "09"], "end_order": ["00", "01", "02", "03", "04", "05", "06", "07", "08", "09"], "run_times": {"00": 1, "01": 1, "02": 1, "03": 1, "04": 1, "05": 1, "06": 1, "07": 1, "08": 1, "09": 1}, "retry_queue": [], "seed": 5141, "seed_state": 5185, "tried_so_far": ["562748b616cb208292193e02f08db7a4", "cf1b01552fc0ab1f6e921e8c7d9ce7e3", "5bc8277bff32b88a1d515169d66bfe54", "ee8e0a8da9f54f096e08247eb6fd5f9c", "9eaf8e7616e23b866f9c0bc7b8bf566c", "0aa7753a76290d2d879adef7bdf86f37", "da4abfde9cb581b33323e0c77cde8f19", "131fba1d50378c61cbc5d6ba1ca5c3bd", "952a9e7c6e1b8412bac0e21ec28dd900", "5c2b1d4d2c26e3d0dee2ce08a557f3d4"], "id_to_hash": {"00": "562748b616cb208292193e02f08db7a4", "01": "131fba1d50378c61cbc5d6ba1ca5c3bd", "02": "da4abfde9cb581b33323e0c77cde8f19", "03": "ee8e0a8da9f54f096e08247eb6fd5f9c", "04": "952a9e7c6e1b8412bac0e21ec28dd900", "05": "9eaf8e7616e23b866f9c0bc7b8bf566c", "06": "5c2b1d4d2c26e3d0dee2ce08a557f3d4", "07": "0aa7753a76290d2d879adef7bdf86f37", "08": "5bc8277bff32b88a1d515169d66bfe54", "09": "cf1b01552fc0ab1f6e921e8c7d9ce7e3"}, "display": {"search_start": "2025-12-25T20:58:56.771597", "trial_start": {"00": "2025-12-25T20:58:56.771597", "01": "2025-12-25T20:59:45.291300", "02": "2025-12-25T21:01:25.594487", "03": "2025-12-25T21:02:41.901629", "04": "2025-12-25T21:03:28.337029", "05": "2025-12-25T21:04:10.614394", "06": "2025-12-25T21:04:58.154358", "07": "2025-12-25T21:05:44.503354", "08": "2025-12-25T21:06:28.973595", "09": "2025-12-25T21:07:14.561684"}, "trial_number": {"00": 1, "01": 2, "02": 3, "03": 4, "04": 5, "05": 6, "06": 7, "07": 8, "08": 9, "09": 10}}}